gistlick/__init__.py
gistlick/main.py
gistlick-0.0.1.dist-info/licenses/LICENSE
gistlick-0.0.1.dist-info/METADATA
gistlick-0.0.1.dist-info/WHEEL
gistlick-0.0.1.dist-info/top_level.txt
gistlick-0.0.1.dist-info/RECORD
