Metadata-Version: 2.4
Name: gistlick
Version: 0.0.1
Summary: Python Library for Create and Manage License Key with GitHub Gists
Author-email: Moh Iqbal Hidayat <iqbalmh18.dev@gmail.com>
License: MIT License
Project-URL: Homepage, https://pypi.org/project/gistlick
Project-URL: Source, https://github.com/iqbalmh18/gistlick
Keywords: gist,github,license,key,management,licensing
Classifier: Programming Language :: Python :: 3
Classifier: License :: OSI Approved :: MIT License
Classifier: Operating System :: OS Independent
Requires-Python: >=3.7
License-File: LICENSE
Requires-Dist: requests
Dynamic: license-file
